yayc/__init__.py
yayc/_version.py
yayc/configurator.py
yayc/test_data/__init__.py
yayc-0.0.2.dist-info/METADATA
yayc-0.0.2.dist-info/WHEEL
yayc-0.0.2.dist-info/top_level.txt
yayc-0.0.2.dist-info/RECORD
