Metadata-Version: 2.1
Name: yayc
Version: 0.0.2
Summary: Yet another YAML configuration library
Home-page: https://github.com/cositools/yayc
Author: COSI Team
Author-email: imc@umd.edu
License: UNKNOWN
Platform: UNKNOWN
Requires-Dist: pyyaml
